virtualenv_reproducible.py
virtualenv_reproducible-0.1.0.post0.dist-info/entry_points.txt
virtualenv_reproducible-0.1.0.post0.dist-info/LICENSE
virtualenv_reproducible-0.1.0.post0.dist-info/WHEEL
virtualenv_reproducible-0.1.0.post0.dist-info/METADATA
virtualenv_reproducible-0.1.0.post0.dist-info/RECORD
